odoo10_addon_crm_claim_code-10.0.1.0.0-py2.7-nspkg.pth
odoo/addons/crm_claim_code/README.rst
odoo/addons/crm_claim_code/__init__.py
odoo/addons/crm_claim_code/__manifest__.py
odoo/addons/crm_claim_code/data/claim_sequence.xml
odoo/addons/crm_claim_code/i18n/bg.po
odoo/addons/crm_claim_code/i18n/de.po
odoo/addons/crm_claim_code/i18n/es.po
odoo/addons/crm_claim_code/i18n/es_MX.po
odoo/addons/crm_claim_code/i18n/es_VE.po
odoo/addons/crm_claim_code/i18n/fr.po
odoo/addons/crm_claim_code/i18n/hr.po
odoo/addons/crm_claim_code/i18n/nb.po
odoo/addons/crm_claim_code/i18n/pt_BR.po
odoo/addons/crm_claim_code/i18n/sk.po
odoo/addons/crm_claim_code/i18n/sl.po
odoo/addons/crm_claim_code/i18n/sv.po
odoo/addons/crm_claim_code/models/__init__.py
odoo/addons/crm_claim_code/models/crm_claim.py
odoo/addons/crm_claim_code/tests/__init__.py
odoo/addons/crm_claim_code/tests/test_crm_claim_code.py
odoo/addons/crm_claim_code/views/crm_claim_view.xml
odoo10_addon_crm_claim_code-10.0.1.0.0.dist-info/DESCRIPTION.rst
odoo10_addon_crm_claim_code-10.0.1.0.0.dist-info/METADATA
odoo10_addon_crm_claim_code-10.0.1.0.0.dist-info/RECORD
odoo10_addon_crm_claim_code-10.0.1.0.0.dist-info/WHEEL
odoo10_addon_crm_claim_code-10.0.1.0.0.dist-info/metadata.json
odoo10_addon_crm_claim_code-10.0.1.0.0.dist-info/namespace_packages.txt
odoo10_addon_crm_claim_code-10.0.1.0.0.dist-info/top_level.txt
